examples/action_dann/__init__.py
examples/action_dann/config.py
examples/action_dann/main.py
examples/action_dann/model.py
examples/action_dann/test.py
examples/bindingdb_deepdta/__init__.py
examples/bindingdb_deepdta/config.py
examples/bindingdb_deepdta/main.py
examples/bindingdb_deepdta/model.py
examples/cifar_cnntransformer/__init__.py
examples/cifar_cnntransformer/config.py
examples/cifar_cnntransformer/main.py
examples/cifar_cnntransformer/model.py
examples/cifar_isonet/__init__.py
examples/cifar_isonet/config.py
examples/cifar_isonet/main.py
examples/cifar_isonet/model.py
examples/cifar_isonet/trainer.py
examples/cmri_mpca/__init__.py
examples/cmri_mpca/config.py
examples/cmri_mpca/main.py
examples/digits_dann/__init__.py
examples/digits_dann/config.py
examples/digits_dann/main.py
examples/digits_dann/model.py
examples/landmark_uncertainty_qbin/__init__.py
examples/multisite_neuroimg_adapt/__init__.py
examples/multisite_neuroimg_adapt/config.py
examples/office_multisource_adapt/__init__.py
examples/office_multisource_adapt/config.py
examples/office_multisource_adapt/main.py
examples/office_multisource_adapt/model.py
examples/polypharmacy_gripnet/__init__.py
examples/polypharmacy_gripnet/config.py
examples/polypharmacy_gripnet/main.py
examples/polypharmacy_gripnet/model.py
examples/toy_domain_adaptation/__init__.py
examples/toy_domain_adaptation/main.py
kale/__init__.py
kale/embed/__init__.py
kale/embed/attention_cnn.py
kale/embed/factorization.py
kale/embed/gcn.py
kale/embed/gripnet.py
kale/embed/image_cnn.py
kale/embed/positional_encoding.py
kale/embed/seq_nn.py
kale/embed/video_feature_extractor.py
kale/embed/video_i3d.py
kale/embed/video_res3d.py
kale/embed/video_se_i3d.py
kale/embed/video_se_res3d.py
kale/embed/video_selayer.py
kale/evaluate/__init__.py
kale/evaluate/metrics.py
kale/interpret/__init__.py
kale/interpret/model_weights.py
kale/interpret/visualize.py
kale/loaddata/__init__.py
kale/loaddata/dataset_access.py
kale/loaddata/image_access.py
pykale-0.1.2.dist-info/LICENSE
pykale-0.1.2.dist-info/METADATA
pykale-0.1.2.dist-info/WHEEL
pykale-0.1.2.dist-info/top_level.txt
pykale-0.1.2.dist-info/RECORD
