Metadata-Version: 2.1
Name: pykale
Version: 0.1.2
Summary: Knowledge-aware machine learning from multiple sources in Python
Home-page: https://github.com/pykale/pykale
Author: The PyKale team
Author-email: pykale-group@sheffield.ac.uk
License: MIT
Project-URL: Bug Tracker, https://github.com/pykale/pykale/issues
Project-URL: Documentation, https://pykale.readthedocs.io
Project-URL: Source, https://github.com/pykale/pykale
Keywords: machine learning,pytorch,deep learning,multimodal learning,transfer learning
Platform: UNKNOWN
Classifier: Intended Audience :: Developers
Classifier: Intended Audience :: Education
Classifier: Intended Audience :: Healthcare Industry
Classifier: Intended Audience :: Science/Research
Classifier: License :: OSI Approved :: MIT License
Classifier: Operating System :: OS Independent
Classifier: Programming Language :: Python :: 3
Classifier: Topic :: Scientific/Engineering :: Artificial Intelligence
Classifier: Topic :: Scientific/Engineering :: Medical Science Apps.
Classifier: Topic :: Software Development :: Libraries
Classifier: Natural Language :: English
Requires-Python: >=3.8,<3.11
License-File: LICENSE
Requires-Dist: numpy (>=1.18.0)
Requires-Dist: pandas
Requires-Dist: pytorch-lightning (<=1.6.5,>=1.3.0)
Requires-Dist: scikit-learn (>=0.23.2)
Requires-Dist: scipy (>=1.5.4)
Requires-Dist: tensorly (<=0.7.0,>=0.5.1)
Requires-Dist: torch (>=1.11.0)
Requires-Dist: torchvision (>=0.12.0)
Provides-Extra: dev
Requires-Dist: networkx ; extra == 'dev'
Requires-Dist: PyTDC (<=0.3.6) ; extra == 'dev'
Requires-Dist: glob2 ; extra == 'dev'
Requires-Dist: pydicom ; extra == 'dev'
Requires-Dist: pylibjpeg ; extra == 'dev'
Requires-Dist: python-gdcm ; extra == 'dev'
Requires-Dist: scikit-image (>=0.16.2) ; extra == 'dev'
Requires-Dist: ipykernel ; extra == 'dev'
Requires-Dist: ipython (<=8.12.0) ; extra == 'dev'
Requires-Dist: matplotlib (<=3.5.2) ; extra == 'dev'
Requires-Dist: nilearn (>=0.7.0) ; extra == 'dev'
Requires-Dist: Pillow ; extra == 'dev'
Requires-Dist: PyTDC ; extra == 'dev'
Requires-Dist: seaborn ; extra == 'dev'
Requires-Dist: torchsummary (>=1.5.0) ; extra == 'dev'
Requires-Dist: yacs (>=0.1.7) ; extra == 'dev'
Requires-Dist: black (==19.10b0) ; extra == 'dev'
Requires-Dist: coverage ; extra == 'dev'
Requires-Dist: flake8 ; extra == 'dev'
Requires-Dist: flake8-print ; extra == 'dev'
Requires-Dist: ipywidgets ; extra == 'dev'
Requires-Dist: isort ; extra == 'dev'
Requires-Dist: m2r ; extra == 'dev'
Requires-Dist: mypy ; extra == 'dev'
Requires-Dist: nbmake (>=0.8) ; extra == 'dev'
Requires-Dist: nbsphinx ; extra == 'dev'
Requires-Dist: nbsphinx-link ; extra == 'dev'
Requires-Dist: nbval ; extra == 'dev'
Requires-Dist: pre-commit ; extra == 'dev'
Requires-Dist: pytest ; extra == 'dev'
Requires-Dist: pytest-cov ; extra == 'dev'
Requires-Dist: recommonmark ; extra == 'dev'
Requires-Dist: sphinx ; extra == 'dev'
Requires-Dist: sphinx-rtd-theme ; extra == 'dev'
Provides-Extra: example
Requires-Dist: ipykernel ; extra == 'example'
Requires-Dist: ipython (<=8.12.0) ; extra == 'example'
Requires-Dist: matplotlib (<=3.5.2) ; extra == 'example'
Requires-Dist: nilearn (>=0.7.0) ; extra == 'example'
Requires-Dist: Pillow ; extra == 'example'
Requires-Dist: PyTDC ; extra == 'example'
Requires-Dist: seaborn ; extra == 'example'
Requires-Dist: torchsummary (>=1.5.0) ; extra == 'example'
Requires-Dist: yacs (>=0.1.7) ; extra == 'example'
Provides-Extra: full
Requires-Dist: networkx ; extra == 'full'
Requires-Dist: PyTDC (<=0.3.6) ; extra == 'full'
Requires-Dist: glob2 ; extra == 'full'
Requires-Dist: pydicom ; extra == 'full'
Requires-Dist: pylibjpeg ; extra == 'full'
Requires-Dist: python-gdcm ; extra == 'full'
Requires-Dist: scikit-image (>=0.16.2) ; extra == 'full'
Requires-Dist: ipykernel ; extra == 'full'
Requires-Dist: ipython (<=8.12.0) ; extra == 'full'
Requires-Dist: matplotlib (<=3.5.2) ; extra == 'full'
Requires-Dist: nilearn (>=0.7.0) ; extra == 'full'
Requires-Dist: Pillow ; extra == 'full'
Requires-Dist: PyTDC ; extra == 'full'
Requires-Dist: seaborn ; extra == 'full'
Requires-Dist: torchsummary (>=1.5.0) ; extra == 'full'
Requires-Dist: yacs (>=0.1.7) ; extra == 'full'
Provides-Extra: graph
Requires-Dist: networkx ; extra == 'graph'
Requires-Dist: PyTDC (<=0.3.6) ; extra == 'graph'
Provides-Extra: image
Requires-Dist: glob2 ; extra == 'image'
Requires-Dist: pydicom ; extra == 'image'
Requires-Dist: pylibjpeg ; extra == 'image'
Requires-Dist: python-gdcm ; extra == 'image'
Requires-Dist: scikit-image (>=0.16.2) ; extra == 'image'
